createfastapiapp/__init__.py
createfastapiapp/cli.py
createfastapiapp/createapp.py
createfastapiapp/assets/example.txt
make_fastapi_app-1.0.7.dist-info/LICENSE
make_fastapi_app-1.0.7.dist-info/METADATA
make_fastapi_app-1.0.7.dist-info/WHEEL
make_fastapi_app-1.0.7.dist-info/entry_points.txt
make_fastapi_app-1.0.7.dist-info/top_level.txt
make_fastapi_app-1.0.7.dist-info/RECORD
