Metadata-Version: 2.1
Name: make-fastapi-app
Version: 1.0.7
Summary: Creates a FastAPI app that is ready to be deployed on Docker hosts like DigitalOcean / Render.com
Home-page: https://github.com/zackees/createfastapiapp
Maintainer: Zachary Vorhies
License: BSD 3-Clause License
Keywords: template-python-cmd
Classifier: Programming Language :: Python :: 3
Requires-Python: >=3.7
License-File: LICENSE
Provides-Extra: dev
Requires-Dist: black; extra == "dev"
Requires-Dist: isort; extra == "dev"
Requires-Dist: flake8; extra == "dev"
Requires-Dist: mypy; extra == "dev"
Requires-Dist: pylint; extra == "dev"
Requires-Dist: pytest; extra == "dev"
Requires-Dist: tox; extra == "dev"
